{
	"configurations" : 
	[
		{
			"directories" : 
			[
				{
					"build" : ".",
					"jsonFile" : "directory-.-Debug-f5ebdc15457944623624.json",
					"minimumCMakeVersion" : 
					{
						"string" : "3.28"
					},
					"projectIndex" : 0,
					"source" : ".",
					"targetIndexes" : 
					[
						0,
						1
					]
				}
			],
			"name" : "Debug",
			"projects" : 
			[
				{
					"directoryIndexes" : 
					[
						0
					],
					"name" : "InterProcessCommunication",
					"targetIndexes" : 
					[
						0,
						1
					]
				}
			],
			"targets" : 
			[
				{
					"directoryIndex" : 0,
					"id" : "client::@6890427a1f51a3e7e1df",
					"jsonFile" : "target-client-Debug-363b126835ae793cb8a8.json",
					"name" : "client",
					"projectIndex" : 0
				},
				{
					"directoryIndex" : 0,
					"id" : "server::@6890427a1f51a3e7e1df",
					"jsonFile" : "target-server-Debug-395a8dd37fe43a93017e.json",
					"name" : "server",
					"projectIndex" : 0
				}
			]
		}
	],
	"kind" : "codemodel",
	"paths" : 
	{
		"build" : "/Users/jiayinglyu/CLionProjects/OS/InterProcessCommunication/cmake-build-debug",
		"source" : "/Users/jiayinglyu/CLionProjects/OS/InterProcessCommunication"
	},
	"version" : 
	{
		"major" : 2,
		"minor" : 6
	}
}
